FoxDotSupriya/SynthDef.py
FoxDotSupriya/__init__.py
FoxDotSupriya/synthdefs/__init__.py
FoxDotSupriya/synthdefs/sine.py
FoxDotSupriya/synthdefs/wsaw.py
foxdotsupriya-0.1.1.dist-info/METADATA
foxdotsupriya-0.1.1.dist-info/WHEEL
foxdotsupriya-0.1.1.dist-info/licenses/LICENSE
foxdotsupriya-0.1.1.dist-info/RECORD
