Metadata-Version: 2.4
Name: FoxDotSupriya
Version: 0.1.1
Summary: Integration with FoxDot and Supriya to white SynthDefs/Effects.
License: CC-BY-SA-4.0
License-File: LICENSE
Author: taconi
Author-email: igor.taconi@protonmail.com
Requires-Python: ~=3.11
Classifier: Development Status :: 4 - Beta
Classifier: Intended Audience :: Developers
Classifier: License :: OSI Approved :: Apache Software License
Classifier: Programming Language :: Python
Classifier: Programming Language :: Python :: 3
Classifier: Programming Language :: Python :: 3.11
Classifier: Programming Language :: Python :: 3.12
Classifier: Programming Language :: Python :: 3.13
Classifier: Programming Language :: Python :: 3.14
Requires-Dist: supriya (>=25.9b1,<26.0)
